{ "compressionlevel":-1,
 "height":50,
 "infinite":false,
 "layers":[
        {
         "data":[0, 0, 0, 0, 0, 0, 0, 0, 0, 0, 0, 0, 0, 0, 0, 0, 0, 0, 0, 0, 0, 0, 0, 0, 0, 0, 0, 0, 0, 0, 0, 0, 0, 0, 0, 0, 0, 0, 0, 0, 0, 0, 0, 0, 0, 0, 0, 0, 0, 0,
            0, 0, 0, 0, 0, 0, 0, 0, 0, 0, 0, 0, 0, 0, 0, 0, 0, 0, 0, 0, 0, 0, 0, 0, 0, 0, 0, 0, 0, 0, 0, 0, 0, 0, 0, 0, 0, 0, 0, 0, 0, 0, 0, 0, 0, 0, 0, 0, 0, 0,
            0, 0, 0, 0, 0, 0, 0, 0, 0, 0, 0, 0, 0, 0, 0, 0, 0, 0, 0, 0, 0, 0, 0, 0, 0, 0, 0, 0, 0, 0, 0, 0, 0, 0, 0, 0, 0, 0, 0, 0, 0, 0, 0, 0, 0, 0, 0, 0, 0, 0,
            0, 0, 0, 0, 0, 0, 0, 0, 0, 0, 0, 0, 0, 0, 0, 0, 0, 0, 0, 0, 0, 0, 0, 0, 0, 0, 0, 0, 0, 0, 0, 0, 0, 0, 0, 0, 0, 0, 0, 0, 0, 0, 0, 0, 0, 0, 0, 0, 0, 0,
            0, 0, 0, 0, 0, 0, 0, 0, 0, 0, 0, 0, 0, 0, 0, 0, 0, 0, 0, 0, 0, 0, 0, 0, 0, 0, 0, 0, 0, 0, 0, 0, 0, 0, 0, 0, 0, 0, 0, 0, 0, 0, 0, 0, 0, 0, 0, 0, 0, 0,
            0, 0, 0, 0, 0, 0, 0, 0, 0, 0, 0, 0, 0, 0, 0, 0, 0, 0, 0, 0, 0, 0, 0, 0, 0, 0, 0, 0, 0, 0, 0, 0, 0, 0, 0, 0, 0, 0, 0, 0, 0, 0, 0, 0, 0, 0, 0, 0, 0, 0,
            0, 0, 0, 0, 0, 0, 0, 0, 0, 0, 0, 0, 0, 0, 0, 0, 0, 0, 0, 0, 0, 0, 0, 0, 0, 0, 0, 0, 0, 0, 0, 0, 0, 0, 0, 0, 0, 0, 0, 0, 0, 0, 0, 0, 0, 0, 0, 0, 0, 0,
            0, 0, 0, 0, 0, 0, 0, 0, 0, 0, 0, 0, 0, 0, 0, 0, 0, 0, 0, 0, 0, 0, 0, 0, 0, 0, 0, 0, 0, 0, 0, 0, 0, 0, 0, 0, 0, 0, 0, 0, 80, 80, 80, 0, 0, 0, 0, 0, 0, 0,
            0, 0, 0, 0, 0, 0, 0, 0, 0, 80, 80, 80, 80, 80, 80, 80, 0, 0, 0, 0, 0, 0, 0, 0, 0, 0, 0, 0, 0, 0, 0, 0, 0, 0, 0, 0, 0, 0, 0, 0, 0, 0, 0, 0, 0, 0, 0, 0, 0, 0,
            0, 0, 0, 0, 0, 0, 0, 0, 0, 0, 0, 0, 0, 0, 0, 0, 0, 0, 0, 0, 0, 0, 0, 0, 0, 0, 0, 0, 0, 0, 0, 0, 0, 0, 0, 0, 0, 0, 0, 0, 0, 0, 0, 0, 0, 0, 0, 0, 0, 0,
            0, 0, 0, 0, 0, 0, 0, 0, 0, 0, 0, 0, 0, 0, 0, 0, 0, 0, 0, 0, 0, 0, 0, 0, 0, 0, 0, 0, 0, 0, 0, 0, 0, 0, 0, 0, 0, 0, 0, 0, 0, 0, 0, 0, 0, 0, 0, 0, 0, 0,
            0, 0, 0, 0, 0, 0, 0, 0, 0, 0, 0, 0, 0, 0, 0, 0, 0, 0, 0, 0, 0, 0, 0, 0, 0, 0, 0, 0, 0, 0, 0, 0, 0, 0, 0, 0, 0, 0, 0, 0, 0, 0, 0, 0, 0, 0, 0, 0, 0, 0,
            0, 0, 0, 0, 0, 0, 0, 0, 0, 0, 0, 0, 0, 0, 0, 0, 0, 0, 0, 0, 0, 0, 0, 0, 0, 0, 0, 0, 0, 0, 0, 0, 0, 0, 0, 0, 0, 0, 0, 0, 0, 0, 0, 0, 0, 0, 0, 0, 0, 0,
            0, 0, 0, 0, 0, 0, 0, 0, 0, 0, 0, 0, 0, 0, 0, 0, 0, 0, 0, 0, 0, 0, 0, 0, 0, 0, 0, 0, 0, 0, 0, 0, 0, 0, 0, 0, 0, 0, 0, 0, 0, 0, 0, 0, 0, 0, 0, 0, 0, 0,
            0, 0, 0, 0, 0, 0, 0, 0, 0, 0, 0, 0, 0, 0, 0, 0, 0, 0, 0, 0, 0, 0, 0, 0, 0, 0, 0, 0, 0, 0, 0, 0, 0, 0, 0, 0, 0, 0, 0, 0, 0, 0, 0, 0, 0, 0, 0, 0, 0, 0,
            0, 0, 0, 0, 0, 0, 0, 0, 0, 0, 0, 0, 0, 0, 0, 0, 0, 0, 0, 0, 0, 0, 0, 80, 0, 0, 0, 0, 0, 0, 0, 0, 0, 0, 0, 0, 0, 0, 0, 0, 0, 0, 0, 0, 0, 0, 0, 0, 0, 0,
            0, 0, 0, 0, 0, 0, 0, 0, 0, 0, 0, 0, 0, 0, 0, 0, 0, 0, 0, 0, 0, 0, 0, 0, 0, 0, 0, 0, 0, 0, 0, 0, 0, 0, 0, 0, 0, 0, 0, 0, 0, 0, 0, 0, 0, 0, 0, 0, 0, 0,
            0, 0, 0, 0, 0, 0, 0, 0, 0, 0, 0, 0, 0, 0, 0, 0, 0, 0, 0, 0, 0, 0, 0, 0, 0, 0, 0, 0, 0, 0, 0, 0, 0, 0, 0, 0, 0, 0, 0, 0, 0, 0, 0, 0, 0, 0, 0, 0, 0, 0,
            0, 0, 0, 0, 0, 0, 0, 0, 0, 0, 0, 0, 0, 0, 0, 0, 0, 0, 0, 0, 0, 0, 0, 0, 0, 0, 0, 0, 0, 0, 0, 0, 0, 0, 0, 0, 0, 0, 0, 0, 0, 0, 0, 0, 0, 0, 0, 0, 0, 0,
            0, 0, 0, 0, 0, 0, 0, 80, 80, 80, 80, 80, 0, 0, 0, 0, 0, 0, 0, 0, 0, 0, 0, 0, 0, 0, 0, 0, 0, 0, 0, 0, 0, 0, 0, 0, 0, 0, 0, 0, 0, 0, 0, 0, 0, 0, 0, 0, 0, 0,
            0, 0, 0, 0, 0, 0, 0, 0, 0, 0, 0, 0, 0, 0, 0, 0, 0, 0, 0, 0, 0, 0, 0, 0, 0, 0, 0, 0, 0, 0, 0, 0, 0, 0, 0, 0, 0, 0, 0, 0, 0, 0, 0, 0, 0, 0, 0, 0, 0, 0,
            0, 0, 0, 0, 0, 0, 0, 0, 0, 0, 0, 0, 0, 0, 0, 80, 80, 0, 0, 0, 0, 0, 0, 0, 0, 0, 0, 0, 0, 0, 0, 0, 0, 0, 0, 0, 0, 0, 0, 0, 0, 0, 0, 0, 0, 0, 0, 0, 0, 0,
            0, 0, 0, 0, 0, 0, 0, 0, 0, 0, 0, 0, 0, 0, 0, 0, 0, 0, 0, 0, 0, 0, 0, 0, 0, 0, 0, 0, 0, 0, 0, 0, 0, 0, 0, 0, 0, 0, 0, 0, 0, 0, 0, 0, 0, 0, 0, 0, 0, 0,
            0, 0, 0, 0, 0, 0, 0, 0, 0, 0, 0, 0, 0, 0, 0, 0, 0, 0, 0, 0, 0, 0, 0, 0, 0, 0, 0, 0, 0, 0, 0, 0, 0, 0, 0, 0, 0, 0, 0, 0, 0, 0, 0, 0, 0, 0, 0, 0, 0, 0,
            0, 0, 0, 0, 0, 0, 0, 0, 0, 0, 0, 0, 0, 0, 0, 0, 0, 0, 0, 0, 0, 0, 0, 0, 0, 0, 0, 0, 0, 0, 0, 0, 0, 0, 0, 0, 0, 0, 0, 0, 0, 0, 0, 0, 0, 0, 0, 0, 0, 0,
            0, 0, 0, 0, 0, 0, 0, 0, 0, 0, 0, 0, 0, 0, 0, 0, 0, 0, 0, 0, 0, 0, 0, 0, 0, 0, 0, 0, 0, 0, 0, 0, 0, 0, 0, 0, 0, 0, 0, 0, 0, 0, 0, 0, 0, 0, 0, 0, 0, 0,
            0, 0, 0, 0, 0, 0, 0, 0, 0, 0, 0, 0, 0, 0, 0, 0, 0, 0, 0, 0, 0, 0, 0, 0, 0, 0, 0, 0, 0, 0, 0, 0, 0, 0, 0, 0, 0, 0, 0, 0, 0, 0, 0, 0, 0, 0, 0, 0, 0, 0,
            0, 0, 0, 0, 0, 0, 0, 0, 0, 0, 0, 0, 0, 0, 0, 0, 0, 0, 0, 0, 0, 0, 0, 0, 0, 0, 0, 0, 0, 0, 0, 0, 0, 0, 0, 0, 0, 0, 0, 0, 0, 0, 0, 0, 0, 0, 0, 0, 80, 0,
            0, 0, 0, 0, 0, 0, 0, 0, 0, 0, 0, 0, 0, 0, 0, 0, 0, 0, 0, 0, 0, 0, 0, 0, 0, 0, 0, 0, 0, 0, 0, 0, 0, 0, 0, 0, 0, 0, 0, 0, 0, 0, 0, 0, 0, 0, 0, 0, 0, 0,
            0, 0, 0, 0, 0, 0, 0, 0, 0, 0, 0, 0, 0, 0, 0, 0, 0, 0, 0, 0, 0, 0, 0, 0, 0, 0, 0, 0, 0, 0, 0, 0, 0, 0, 0, 0, 0, 0, 0, 0, 0, 0, 0, 0, 0, 0, 0, 0, 0, 0,
            0, 0, 0, 0, 0, 0, 0, 0, 0, 0, 0, 0, 0, 0, 0, 0, 0, 0, 0, 0, 0, 0, 80, 80, 80, 0, 0, 0, 0, 0, 0, 0, 0, 0, 0, 0, 0, 0, 0, 0, 0, 0, 0, 0, 0, 0, 0, 0, 0, 0,
            0, 0, 0, 0, 0, 0, 0, 0, 80, 80, 80, 0, 0, 0, 0, 0, 0, 0, 0, 0, 0, 0, 0, 0, 0, 0, 0, 0, 0, 0, 0, 0, 0, 0, 0, 0, 0, 0, 0, 0, 0, 0, 0, 0, 0, 0, 0, 0, 0, 0,
            0, 0, 0, 0, 0, 0, 0, 0, 0, 0, 0, 0, 0, 0, 0, 0, 0, 0, 0, 0, 0, 0, 0, 0, 0, 0, 0, 0, 0, 0, 0, 0, 0, 0, 0, 0, 0, 0, 0, 0, 0, 0, 0, 0, 0, 0, 0, 0, 0, 0,
            0, 0, 0, 0, 0, 0, 0, 0, 0, 0, 0, 0, 0, 0, 0, 0, 0, 0, 0, 0, 0, 0, 0, 0, 0, 0, 0, 0, 0, 0, 0, 0, 0, 0, 0, 0, 0, 0, 0, 0, 0, 0, 0, 0, 0, 0, 0, 0, 0, 0,
            0, 0, 0, 0, 0, 0, 0, 0, 0, 0, 0, 0, 0, 0, 0, 0, 0, 0, 0, 0, 0, 0, 0, 0, 0, 0, 0, 0, 0, 0, 0, 0, 0, 0, 0, 0, 0, 0, 0, 0, 0, 0, 0, 0, 0, 0, 0, 0, 0, 0,
            0, 0, 0, 0, 0, 0, 0, 0, 0, 0, 0, 0, 0, 0, 0, 0, 0, 0, 0, 0, 0, 0, 0, 0, 0, 0, 0, 0, 0, 0, 0, 0, 0, 0, 0, 0, 0, 0, 0, 0, 0, 0, 0, 0, 0, 0, 0, 0, 0, 0,
            0, 0, 0, 0, 0, 0, 0, 0, 0, 0, 0, 0, 0, 0, 0, 0, 0, 0, 0, 0, 0, 0, 0, 0, 0, 0, 0, 0, 0, 0, 0, 0, 0, 0, 0, 0, 0, 0, 0, 0, 0, 0, 0, 0, 0, 0, 0, 0, 0, 0,
            0, 0, 0, 0, 0, 0, 0, 0, 0, 0, 0, 0, 0, 0, 0, 0, 0, 0, 0, 0, 0, 0, 0, 0, 0, 0, 0, 0, 0, 0, 0, 0, 0, 0, 80, 0, 0, 0, 0, 0, 0, 0, 0, 0, 0, 0, 0, 0, 0, 0,
            0, 0, 0, 0, 0, 0, 0, 0, 0, 0, 0, 0, 0, 0, 0, 0, 0, 0, 0, 0, 0, 0, 0, 0, 0, 0, 0, 0, 0, 0, 0, 0, 0, 0, 0, 0, 0, 0, 0, 0, 0, 0, 0, 0, 0, 0, 0, 0, 0, 0,
            0, 0, 0, 0, 0, 0, 0, 0, 0, 0, 0, 0, 0, 0, 0, 0, 0, 0, 0, 0, 0, 0, 0, 0, 0, 0, 0, 0, 0, 0, 0, 0, 0, 0, 0, 0, 0, 0, 0, 0, 0, 0, 0, 0, 0, 0, 0, 0, 0, 0,
            0, 0, 0, 0, 0, 0, 0, 0, 0, 0, 0, 0, 0, 0, 0, 0, 0, 0, 0, 0, 0, 0, 0, 0, 0, 0, 0, 0, 0, 0, 0, 0, 0, 0, 0, 0, 0, 0, 0, 0, 0, 0, 0, 0, 0, 0, 0, 0, 0, 0,
            0, 0, 0, 0, 0, 0, 0, 0, 0, 0, 0, 0, 0, 0, 0, 0, 0, 0, 0, 0, 0, 0, 0, 0, 0, 0, 0, 0, 0, 0, 0, 0, 0, 0, 0, 0, 0, 0, 0, 0, 0, 0, 0, 0, 0, 0, 0, 0, 0, 0,
            0, 0, 0, 0, 0, 0, 0, 0, 0, 0, 80, 80, 0, 0, 0, 0, 0, 80, 80, 80, 0, 0, 0, 0, 0, 0, 0, 0, 0, 0, 0, 0, 0, 0, 0, 0, 0, 0, 0, 0, 0, 0, 0, 0, 0, 0, 0, 0, 0, 0,
            0, 0, 0, 0, 0, 0, 0, 0, 0, 0, 0, 0, 0, 0, 0, 0, 0, 0, 0, 0, 0, 0, 0, 0, 0, 0, 0, 0, 0, 0, 0, 0, 0, 0, 0, 0, 0, 0, 0, 0, 0, 0, 0, 0, 0, 0, 0, 0, 0, 0,
            0, 0, 0, 0, 0, 0, 0, 0, 0, 0, 0, 0, 0, 0, 0, 0, 0, 0, 0, 0, 0, 0, 0, 80, 80, 0, 0, 0, 0, 0, 0, 0, 0, 0, 0, 0, 0, 0, 0, 0, 0, 0, 0, 0, 0, 0, 0, 0, 0, 0,
            0, 0, 0, 0, 0, 0, 0, 0, 0, 0, 0, 0, 0, 0, 0, 0, 0, 0, 0, 0, 0, 0, 0, 0, 0, 0, 0, 0, 0, 80, 80, 80, 80, 80, 80, 80, 80, 0, 0, 0, 0, 0, 0, 0, 0, 0, 0, 0, 0, 0,
            0, 0, 0, 0, 0, 0, 0, 0, 0, 0, 0, 0, 0, 0, 0, 0, 0, 0, 0, 0, 0, 0, 0, 0, 0, 0, 0, 0, 0, 0, 0, 0, 0, 0, 0, 0, 0, 0, 0, 0, 0, 0, 0, 0, 0, 0, 0, 0, 0, 0,
            0, 0, 0, 0, 0, 0, 0, 0, 0, 0, 0, 0, 0, 0, 0, 0, 0, 0, 0, 0, 0, 0, 0, 0, 0, 0, 0, 0, 0, 0, 0, 0, 0, 0, 0, 0, 0, 0, 0, 0, 0, 0, 0, 0, 0, 0, 0, 0, 0, 0,
            0, 0, 0, 0, 0, 0, 0, 0, 0, 0, 0, 0, 0, 0, 0, 0, 0, 0, 0, 0, 0, 0, 0, 0, 0, 0, 0, 0, 0, 0, 0, 0, 0, 0, 0, 0, 0, 0, 0, 0, 0, 0, 0, 0, 0, 0, 0, 0, 0, 0,
            0, 0, 0, 0, 0, 0, 0, 0, 0, 0, 0, 0, 0, 0, 0, 0, 0, 0, 0, 0, 0, 0, 0, 0, 0, 0, 0, 0, 0, 0, 0, 0, 0, 0, 0, 0, 0, 0, 0, 0, 0, 0, 0, 0, 0, 0, 0, 0, 0, 0],
         "height":50,
         "id":3,
         "name":"calque_de_pique",
         "opacity":1,
         "type":"tilelayer",
         "visible":true,
         "width":50,
         "x":0,
         "y":0
        }, 
        {
         "data":[0, 0, 0, 0, 0, 0, 0, 0, 0, 0, 0, 0, 0, 0, 0, 0, 0, 0, 0, 0, 0, 0, 0, 0, 0, 0, 0, 0, 0, 0, 0, 0, 0, 0, 0, 0, 0, 0, 0, 0, 0, 0, 0, 0, 0, 0, 0, 0, 0, 0,
            91, 91, 91, 91, 91, 91, 91, 91, 91, 91, 91, 91, 91, 91, 91, 91, 91, 91, 91, 91, 91, 91, 91, 91, 91, 0, 0, 0, 91, 91, 91, 91, 91, 91, 91, 91, 0, 0, 0, 0, 0, 0, 0, 0, 0, 0, 0, 0, 0, 0,
            91, 0, 0, 0, 0, 0, 0, 0, 0, 0, 0, 0, 0, 0, 0, 0, 0, 0, 0, 0, 0, 0, 0, 0, 91, 0, 0, 0, 91, 0, 0, 0, 0, 0, 0, 91, 0, 0, 0, 0, 0, 0, 0, 0, 0, 0, 0, 0, 0, 0,
            91, 0, 0, 0, 0, 0, 0, 0, 0, 0, 0, 0, 0, 0, 0, 0, 0, 0, 0, 0, 0, 0, 0, 0, 91, 0, 0, 0, 91, 0, 0, 0, 0, 0, 0, 91, 0, 0, 0, 0, 0, 0, 0, 0, 0, 0, 0, 0, 0, 0,
            91, 0, 0, 0, 0, 0, 91, 0, 0, 0, 0, 0, 0, 0, 0, 0, 0, 0, 0, 91, 91, 0, 0, 0, 91, 0, 0, 0, 91, 0, 0, 0, 0, 0, 0, 91, 0, 0, 0, 0, 0, 0, 0, 0, 0, 0, 0, 0, 0, 0,
            91, 91, 91, 91, 91, 91, 91, 91, 91, 0, 0, 91, 0, 91, 0, 0, 91, 91, 91, 91, 91, 0, 0, 0, 91, 0, 0, 0, 91, 0, 0, 0, 91, 91, 91, 91, 0, 0, 0, 0, 0, 0, 0, 0, 0, 0, 0, 0, 0, 0,
            0, 0, 0, 0, 0, 0, 0, 0, 91, 0, 0, 0, 0, 0, 0, 0, 91, 0, 0, 0, 91, 0, 0, 0, 91, 0, 0, 0, 91, 0, 0, 0, 91, 0, 0, 0, 91, 91, 91, 91, 91, 91, 91, 91, 0, 0, 0, 0, 0, 0,
            0, 0, 0, 0, 0, 0, 0, 0, 91, 0, 0, 0, 0, 0, 0, 0, 91, 0, 0, 0, 91, 0, 0, 0, 91, 0, 0, 0, 91, 0, 0, 0, 91, 0, 0, 0, 91, 0, 0, 0, 0, 0, 0, 91, 0, 0, 0, 0, 0, 0,
            0, 0, 0, 0, 0, 0, 0, 0, 91, 0, 0, 0, 0, 0, 0, 0, 91, 0, 0, 0, 91, 0, 0, 0, 91, 0, 0, 0, 91, 0, 0, 0, 91, 0, 0, 0, 91, 0, 0, 0, 0, 0, 0, 91, 0, 0, 0, 0, 0, 0,
            91, 91, 91, 91, 91, 91, 91, 91, 91, 91, 91, 91, 91, 91, 91, 91, 91, 0, 0, 0, 91, 0, 0, 0, 91, 0, 0, 0, 91, 0, 0, 0, 91, 0, 0, 0, 91, 0, 0, 0, 0, 0, 0, 91, 0, 0, 0, 0, 0, 0,
            91, 0, 0, 0, 0, 0, 0, 0, 91, 0, 0, 0, 0, 0, 0, 0, 91, 91, 91, 91, 91, 0, 0, 0, 91, 0, 0, 0, 91, 0, 0, 0, 91, 0, 0, 0, 91, 0, 0, 0, 91, 91, 91, 91, 0, 0, 0, 0, 0, 0,
            91, 0, 0, 0, 0, 0, 0, 0, 91, 91, 91, 91, 91, 91, 91, 91, 91, 0, 0, 0, 0, 0, 0, 0, 91, 0, 0, 0, 91, 0, 0, 0, 91, 0, 0, 0, 91, 0, 0, 0, 91, 0, 0, 0, 0, 0, 0, 0, 0, 0,
            91, 0, 0, 0, 0, 0, 0, 0, 0, 0, 0, 0, 0, 0, 0, 0, 0, 0, 0, 0, 0, 0, 0, 0, 91, 91, 91, 91, 91, 0, 0, 0, 91, 0, 0, 0, 91, 0, 0, 0, 91, 0, 0, 0, 0, 0, 0, 0, 0, 0,
            91, 0, 0, 0, 0, 0, 0, 0, 0, 0, 0, 0, 0, 0, 0, 0, 0, 0, 0, 0, 0, 0, 0, 0, 0, 0, 0, 0, 0, 0, 0, 0, 91, 0, 0, 0, 91, 0, 0, 0, 91, 0, 0, 0, 0, 0, 0, 0, 0, 0,
            91, 0, 0, 0, 0, 0, 0, 0, 0, 0, 0, 0, 0, 0, 0, 0, 0, 0, 0, 0, 0, 0, 0, 0, 0, 0, 0, 0, 0, 0, 0, 91, 91, 0, 0, 0, 91, 0, 0, 0, 91, 0, 0, 0, 0, 0, 0, 0, 0, 0,
            91, 0, 0, 91, 91, 91, 91, 0, 0, 91, 0, 0, 91, 91, 91, 0, 0, 91, 91, 91, 91, 0, 0, 0, 91, 91, 91, 91, 91, 0, 0, 91, 0, 0, 0, 0, 91, 0, 0, 0, 91, 0, 0, 0, 0, 0, 0, 0, 0, 0,
            91, 0, 0, 91, 0, 0, 91, 0, 0, 0, 0, 0, 91, 0, 91, 0, 0, 91, 0, 0, 91, 91, 91, 91, 91, 0, 0, 0, 91, 91, 91, 91, 0, 0, 0, 0, 91, 0, 0, 0, 91, 0, 0, 0, 0, 0, 0, 0, 0, 0,
            91, 0, 0, 91, 0, 0, 91, 0, 0, 0, 0, 0, 91, 91, 91, 0, 0, 91, 0, 0, 0, 0, 0, 0, 0, 0, 0, 0, 0, 0, 0, 0, 0, 0, 0, 0, 91, 0, 0, 0, 91, 0, 0, 0, 0, 0, 0, 0, 0, 0,
            91, 0, 0, 91, 0, 0, 91, 0, 0, 0, 0, 0, 91, 91, 91, 0, 0, 91, 91, 91, 91, 91, 91, 0, 0, 0, 0, 0, 0, 0, 0, 0, 0, 0, 0, 0, 91, 0, 0, 0, 91, 0, 0, 0, 0, 0, 0, 0, 0, 0,
            91, 0, 0, 91, 0, 0, 91, 0, 0, 0, 0, 0, 91, 0, 0, 0, 0, 0, 0, 0, 0, 0, 91, 0, 0, 0, 0, 0, 0, 0, 0, 0, 0, 0, 0, 0, 91, 0, 0, 0, 91, 0, 0, 0, 0, 0, 0, 0, 0, 0,
            91, 0, 0, 91, 0, 0, 91, 91, 91, 91, 91, 91, 91, 0, 0, 0, 0, 0, 0, 0, 0, 0, 91, 0, 0, 0, 0, 0, 0, 0, 0, 0, 0, 0, 0, 0, 91, 0, 0, 0, 91, 0, 0, 0, 0, 0, 0, 0, 0, 0,
            91, 0, 0, 91, 0, 0, 0, 0, 0, 0, 0, 0, 91, 0, 0, 0, 0, 0, 0, 0, 0, 0, 91, 0, 0, 0, 0, 0, 0, 0, 0, 0, 0, 0, 0, 0, 91, 0, 0, 0, 91, 0, 0, 0, 0, 0, 0, 0, 0, 0,
            91, 0, 0, 91, 0, 0, 0, 0, 0, 0, 0, 0, 0, 91, 91, 91, 91, 91, 91, 91, 91, 91, 91, 0, 0, 0, 0, 0, 0, 0, 0, 0, 0, 0, 0, 0, 91, 0, 0, 0, 91, 0, 0, 0, 0, 0, 0, 0, 0, 0,
            91, 0, 0, 91, 0, 0, 0, 0, 0, 0, 0, 0, 0, 0, 0, 0, 0, 0, 0, 0, 0, 0, 0, 0, 0, 0, 0, 0, 0, 0, 0, 0, 0, 0, 0, 0, 91, 0, 0, 0, 91, 0, 0, 0, 0, 0, 0, 0, 0, 0,
            91, 0, 0, 91, 91, 91, 91, 91, 91, 91, 91, 91, 91, 91, 91, 91, 91, 0, 0, 91, 91, 91, 91, 91, 91, 91, 91, 91, 91, 91, 91, 91, 91, 91, 91, 91, 91, 0, 0, 0, 91, 0, 0, 0, 0, 0, 0, 0, 0, 0,
            91, 0, 0, 0, 0, 0, 0, 0, 0, 0, 0, 0, 0, 0, 0, 0, 91, 0, 0, 91, 0, 0, 0, 0, 0, 0, 0, 0, 0, 0, 0, 0, 0, 0, 0, 0, 0, 0, 0, 0, 91, 0, 0, 0, 0, 0, 0, 0, 0, 0,
            91, 0, 0, 0, 0, 0, 0, 0, 0, 0, 0, 0, 0, 0, 0, 0, 91, 0, 0, 91, 0, 0, 0, 0, 0, 0, 0, 0, 0, 0, 0, 0, 0, 0, 0, 0, 0, 0, 0, 91, 91, 0, 0, 0, 91, 91, 91, 91, 91, 91,
            91, 0, 0, 0, 0, 0, 0, 0, 0, 0, 0, 0, 0, 0, 0, 0, 91, 0, 0, 91, 0, 0, 0, 0, 0, 0, 0, 0, 0, 0, 0, 0, 0, 0, 0, 0, 0, 0, 0, 91, 0, 0, 0, 0, 91, 0, 0, 0, 0, 91,
            91, 0, 0, 0, 91, 91, 91, 91, 0, 0, 0, 0, 0, 0, 0, 0, 91, 0, 0, 91, 0, 0, 91, 91, 91, 91, 91, 91, 91, 91, 91, 91, 91, 91, 91, 91, 91, 91, 91, 91, 0, 0, 0, 0, 91, 0, 0, 0, 0, 91,
            91, 91, 91, 91, 91, 0, 0, 91, 0, 0, 0, 91, 91, 91, 0, 0, 91, 0, 0, 91, 0, 0, 91, 91, 91, 91, 91, 91, 91, 91, 91, 91, 91, 91, 91, 91, 91, 91, 91, 0, 0, 0, 0, 0, 91, 0, 0, 0, 0, 91,
            0, 0, 0, 0, 0, 0, 0, 91, 0, 0, 0, 91, 0, 91, 0, 0, 91, 0, 0, 91, 0, 0, 0, 0, 0, 0, 0, 0, 0, 0, 0, 0, 0, 0, 0, 0, 0, 0, 91, 0, 0, 0, 0, 0, 91, 0, 0, 0, 91, 91,
            0, 0, 0, 0, 0, 0, 0, 91, 0, 0, 0, 91, 0, 91, 0, 0, 91, 0, 0, 91, 0, 0, 0, 0, 0, 0, 0, 0, 0, 0, 0, 0, 0, 0, 0, 0, 0, 0, 91, 0, 0, 0, 0, 0, 91, 0, 0, 0, 0, 91,
            0, 0, 0, 0, 0, 0, 0, 91, 91, 91, 91, 91, 0, 91, 0, 0, 91, 0, 0, 91, 0, 0, 0, 0, 0, 0, 0, 0, 0, 0, 0, 0, 0, 0, 0, 0, 0, 0, 91, 91, 91, 91, 91, 91, 91, 91, 91, 0, 0, 91,
            0, 0, 0, 0, 0, 0, 0, 0, 0, 0, 0, 0, 0, 91, 0, 0, 91, 0, 0, 91, 91, 91, 91, 91, 91, 91, 91, 91, 91, 91, 91, 0, 0, 0, 0, 0, 0, 0, 0, 0, 0, 0, 0, 0, 0, 0, 0, 0, 0, 91,
            91, 91, 91, 91, 91, 91, 91, 91, 91, 91, 91, 91, 91, 91, 0, 0, 91, 0, 0, 91, 91, 91, 91, 91, 91, 91, 91, 91, 91, 91, 91, 0, 0, 0, 0, 0, 0, 0, 0, 0, 0, 0, 0, 0, 0, 0, 0, 0, 91, 91,
            91, 0, 0, 0, 0, 0, 0, 0, 0, 0, 0, 0, 0, 0, 0, 0, 91, 91, 91, 91, 0, 0, 0, 0, 0, 0, 0, 0, 0, 0, 0, 0, 0, 91, 91, 0, 0, 0, 0, 0, 0, 0, 0, 0, 0, 0, 0, 0, 0, 91,
            91, 0, 0, 0, 0, 0, 0, 0, 0, 0, 0, 0, 0, 0, 0, 0, 0, 0, 0, 0, 0, 0, 0, 0, 0, 0, 0, 0, 0, 0, 0, 0, 0, 91, 91, 0, 0, 0, 0, 0, 0, 0, 0, 91, 91, 91, 91, 0, 0, 91,
            91, 0, 0, 0, 0, 0, 0, 0, 0, 0, 0, 0, 0, 0, 0, 0, 0, 0, 0, 0, 0, 0, 0, 0, 0, 0, 0, 0, 0, 0, 0, 0, 0, 0, 0, 0, 0, 0, 0, 0, 0, 0, 0, 91, 0, 0, 91, 0, 0, 91,
            91, 0, 0, 0, 0, 0, 0, 0, 0, 0, 0, 0, 0, 0, 0, 0, 0, 0, 0, 0, 0, 0, 0, 0, 0, 0, 0, 0, 0, 0, 0, 0, 0, 0, 0, 0, 0, 91, 91, 91, 0, 0, 0, 91, 0, 0, 91, 0, 0, 91,
            91, 0, 0, 0, 91, 91, 91, 91, 91, 91, 91, 91, 91, 91, 91, 91, 91, 91, 91, 91, 91, 91, 0, 0, 0, 0, 0, 0, 0, 0, 0, 0, 0, 0, 0, 0, 0, 91, 0, 91, 0, 0, 0, 91, 0, 0, 91, 0, 0, 91,
            91, 0, 0, 0, 91, 0, 0, 0, 0, 0, 0, 0, 0, 0, 0, 0, 0, 0, 0, 0, 0, 91, 0, 0, 0, 0, 0, 0, 0, 0, 0, 91, 0, 0, 91, 0, 0, 91, 0, 91, 0, 0, 0, 91, 0, 0, 91, 0, 0, 91,
            91, 0, 0, 0, 91, 91, 91, 91, 91, 91, 91, 91, 91, 91, 91, 91, 91, 91, 91, 91, 91, 91, 0, 0, 0, 0, 0, 91, 91, 0, 0, 0, 0, 0, 0, 0, 0, 91, 0, 91, 0, 0, 0, 91, 0, 0, 91, 0, 0, 91,
            91, 0, 0, 0, 0, 0, 0, 0, 0, 0, 0, 0, 0, 0, 0, 0, 0, 0, 0, 0, 0, 0, 0, 0, 0, 0, 0, 91, 91, 0, 0, 0, 0, 0, 0, 0, 0, 91, 0, 91, 0, 0, 0, 91, 0, 0, 91, 0, 0, 91,
            91, 0, 0, 0, 0, 0, 0, 0, 0, 0, 0, 0, 0, 0, 0, 0, 0, 0, 0, 0, 0, 0, 0, 0, 0, 91, 91, 91, 91, 0, 0, 0, 0, 0, 0, 0, 0, 91, 0, 91, 0, 0, 0, 91, 0, 0, 91, 0, 0, 91,
            91, 0, 0, 0, 0, 0, 0, 0, 0, 0, 0, 0, 0, 0, 0, 0, 0, 0, 0, 0, 0, 0, 0, 0, 0, 91, 0, 0, 91, 0, 0, 0, 0, 0, 0, 0, 0, 91, 0, 91, 0, 0, 0, 91, 0, 0, 91, 0, 0, 91,
            91, 0, 0, 0, 91, 91, 91, 91, 91, 91, 91, 91, 91, 91, 91, 91, 91, 91, 91, 91, 91, 91, 91, 91, 91, 91, 0, 0, 91, 0, 0, 0, 0, 0, 0, 0, 0, 91, 0, 91, 0, 0, 0, 91, 0, 0, 91, 0, 0, 91,
            91, 0, 0, 0, 91, 0, 0, 0, 0, 0, 0, 0, 0, 0, 0, 0, 0, 0, 0, 0, 0, 0, 0, 0, 0, 0, 0, 0, 91, 91, 91, 91, 91, 91, 91, 91, 91, 91, 0, 91, 0, 0, 0, 91, 0, 0, 91, 0, 0, 91,
            91, 0, 0, 0, 91, 0, 0, 0, 0, 0, 0, 0, 0, 0, 0, 0, 0, 0, 0, 0, 0, 0, 0, 0, 0, 0, 0, 0, 0, 0, 0, 0, 0, 0, 0, 0, 0, 0, 0, 91, 0, 0, 0, 91, 0, 0, 91, 0, 0, 91,
            91, 0, 0, 0, 91, 0, 0, 0, 0, 0, 0, 0, 0, 0, 0, 0, 0, 0, 0, 0, 0, 0, 0, 0, 0, 0, 0, 0, 0, 0, 0, 0, 0, 0, 0, 0, 0, 0, 0, 91, 0, 0, 0, 91, 0, 0, 91, 0, 0, 91,
            91, 0, 0, 0, 91, 0, 0, 0, 0, 0, 0, 0, 0, 0, 0, 0, 0, 0, 0, 0, 0, 0, 0, 0, 0, 0, 0, 0, 0, 0, 0, 0, 0, 0, 0, 0, 0, 0, 0, 91, 0, 0, 0, 91, 0, 0, 91, 0, 0, 91],
         "height":50,
         "id":1,
         "name":"calque_de_tuile",
         "opacity":1,
         "type":"tilelayer",
         "visible":true,
         "width":50,
         "x":0,
         "y":0
        }],
 "nextlayerid":4,
 "nextobjectid":1,
 "orientation":"orthogonal",
 "renderorder":"right-down",
 "tiledversion":"1.9.2",
 "tileheight":32,
 "tilesets":[
        {
         "columns":10,
         "firstgid":1,
         "image":"..\/..\/..\/level design\/projet2\/New Piskel update006.png",
         "imageheight":320,
         "imagewidth":320,
         "margin":0,
         "name":"New Piskel update006",
         "spacing":0,
         "tilecount":100,
         "tileheight":32,
         "tiles":[
                {
                 "id":79,
                 "properties":[
                        {
                         "name":"estsolide",
                         "type":"bool",
                         "value":true
                        }]
                }, 
                {
                 "id":90,
                 "properties":[
                        {
                         "name":"estsolide",
                         "type":"bool",
                         "value":true
                        }]
                }],
         "tilewidth":32
        }],
 "tilewidth":32,
 "type":"map",
 "version":"1.9",
 "width":50
}